README.txt
setup.py
pickpaged/__init__.py
pickpaged.egg-info/PKG-INFO
pickpaged.egg-info/SOURCES.txt
pickpaged.egg-info/dependency_links.txt
pickpaged.egg-info/requires.txt
pickpaged.egg-info/top_level.txt