Metadata-Version: 1.1
Name: pickpaged
Version: 1.1.1
Summary: pick an option in the terminal with a simple paged GUI
Home-page: https://github.com/roubles/pickpaged
Author: roubles
Author-email: rouble@gmail.com
License: MIT
Download-URL: https://github.com/roubles/pickpaged/tarball/1.1.1
Platform: UNKNOWN
